dislevel/__init__.py
dislevel/_cog.py
dislevel/_db_adapter.py
dislevel/_models.py
dislevel/_version.py
dislevel/card.py
dislevel/connector.py
dislevel/utils.py
dislevel/assets/bg.png
dislevel/discord/__init__.py
dislevel/discord/slash.py
dislevel/nextcord/__init__.py
dislevel/nextcord/slash.py
dislevel-2.0.3.dist-info/LICENSE
dislevel-2.0.3.dist-info/METADATA
dislevel-2.0.3.dist-info/WHEEL
dislevel-2.0.3.dist-info/top_level.txt
dislevel-2.0.3.dist-info/RECORD
