Metadata-Version: 2.1
Name: dislevel
Version: 2.0.3
Summary: A leveling cog for discord bots
Home-page: https://github.com/shahriyardx/dislevel/
Author: Md Shahriyar Alam
Author-email: mdshahriyaralam552@gmail.com
License: MIT
Project-URL: Bug Reports, https://github.com/shahriyardx/dislevel/issues
Project-URL: Source, https://github.com/shahriyardx/dislevel/
Keywords: discord discord-rank discord-profile discord-leveling
Platform: UNKNOWN
Classifier: Development Status :: 3 - Alpha
Classifier: Intended Audience :: Developers
Classifier: Operating System :: MacOS
Classifier: Operating System :: POSIX :: Linux
Classifier: Operating System :: Microsoft :: Windows
Classifier: License :: OSI Approved :: MIT License
Classifier: Programming Language :: Python :: 3.7
Classifier: Programming Language :: Python :: 3.8
Classifier: Programming Language :: Python :: 3.9
Classifier: Programming Language :: Python :: 3.10
Requires-Python: >=3.7, <4
Requires-Dist: easy-pil (>=0.1.6)
Requires-Dist: numerize (>=0.12)
Requires-Dist: python-dotenv (>=0.20.0)
Requires-Dist: typing-extensions (>=4.2.0)
